Logs/__init__.py
Logs/logs.py
NumWord/__init__.py
NumWord/currency.py
NumWord/humanize_number.py
NumWord/number_to_word.py
NumWord/word_to_number.py
numword-0.0.6.dist-info/licenses/LICENSE
utility/__init__.py
utility/english.py
utility/french.py
utility/hindi.py
utility/symboles.py
numword-0.0.6.dist-info/METADATA
numword-0.0.6.dist-info/WHEEL
numword-0.0.6.dist-info/top_level.txt
numword-0.0.6.dist-info/RECORD
