Metadata-Version: 2.4
Name: NumWord
Version: 0.0.6
Summary: Convert words to numbers, numbers to words, and humanized formats and currency conversion with live rates.
Home-page: https://github.com/HarshitDalal/NumWord
Author: Harshit Dalal
Author-email: harshitdalal96@gmail.com
Keywords: number,word,conversion,numbers2words,number to word,word to number,num2words,words2number,numword
Classifier: Programming Language :: Python :: 3
Classifier: Programming Language :: Python :: 3.6
Classifier: Programming Language :: Python :: 3.7
Classifier: Programming Language :: Python :: 3.8
Classifier: Programming Language :: Python :: 3.9
Classifier: Programming Language :: Python :: 3.10
Classifier: Programming Language :: Python :: 3.11
Classifier: License :: OSI Approved :: MIT License
Classifier: Operating System :: OS Independent
Requires-Python: >=3.6
License-File: LICENSE
Dynamic: author
Dynamic: author-email
Dynamic: classifier
Dynamic: description
Dynamic: description-content-type
Dynamic: home-page
Dynamic: keywords
Dynamic: license-file
Dynamic: requires-python
Dynamic: summary
